sora/app/v1beta/service_pb2.py
sora/app/v1beta/service_pb2_grpc.py
sora/app/v1beta/types_pb2.py
sora/app/v1beta/types_pb2_grpc.py
sora/device/v1beta/service_pb2.py
sora/device/v1beta/service_pb2_grpc.py
sora/v1beta/common_pb2.py
sora/v1beta/common_pb2_grpc.py
sora_device_client/__init__.py
sora_device_client/auth0/__init__.py
sora_device_client/auth0/info.py
sora_device_client/cli/__init__.py
sora_device_client/cli/login.py
sora_device_client/cli/logout.py
sora_device_client/cli/paths.py
sora_device_client/cli/start.py
sora_device_client/client/__init__.py
sora_device_client/config/__init__.py
sora_device_client/config/device.py
sora_device_client/config/server.py
sora_device_client/config_example.toml
sora_device_client/drivers/__init__.py
sora_device_client/exceptions.py
sora_device_client/formats/__init__.py
sora_device_client/formats/sbp.py
sora_device_client/location.py
sora_device_client-1.1.0.dist-info/METADATA
sora_device_client-1.1.0.dist-info/WHEEL
sora_device_client-1.1.0.dist-info/entry_points.txt
sora_device_client-1.1.0.dist-info/RECORD
