Metadata-Version: 2.1
Name: sora-device-client
Version: 1.1.0
Summary: A client to stream device location data to a sever for the SORA api
License: MIT
Author: Swift Navigation
Author-email: dev@swift-nav.com
Requires-Python: >=3.8,<4.0
Classifier: License :: OSI Approved :: MIT License
Classifier: Programming Language :: Python :: 3
Classifier: Programming Language :: Python :: 3.8
Classifier: Programming Language :: Python :: 3.9
Classifier: Programming Language :: Python :: 3.10
Classifier: Programming Language :: Python :: 3.11
Requires-Dist: appdirs (>=1.4.4,<2.0.0)
Requires-Dist: deepmerge (>=1.0.1,<2.0.0)
Requires-Dist: grpcio (==1.51.1)
Requires-Dist: gtfs-realtime-bindings (>=0.0.7,<0.0.8)
Requires-Dist: persist-queue (>=0.8.0,<0.9.0)
Requires-Dist: requests (>=2.28.0,<3.0.0)
Requires-Dist: sbp (>=4.7.0,<5.0.0)
Requires-Dist: tomlkit (>=0.11.4,<0.12.0)
Requires-Dist: typer[all] (>=0.6.1,<0.7.0)
